kimtaewoncoding/__init__.py
kimtaewoncoding/kimtaewoncoding.py
kimtaewoncoding-0.1.dist-info/METADATA
kimtaewoncoding-0.1.dist-info/WHEEL
kimtaewoncoding-0.1.dist-info/top_level.txt
kimtaewoncoding-0.1.dist-info/RECORD
