Metadata-Version: 2.1
Name: kimtaewoncoding
Version: 0.1
Summary: Python functions for controlling Arduino devices
Home-page: UNKNOWN
Author: kimtaewoncoding
Author-email: kimtw5967@gmail.com
License: UNKNOWN
Platform: UNKNOWN
Requires-Dist: pyserial
